hertz_packet/__init__.py
hertz_packet/cleaning/__init__.py
hertz_packet/cleaning/sweeper.py
hertz_packet/crontab/__init__.py
hertz_packet/crontab/sche.py
hertz_packet/notice/__init__.py
hertz_packet/notice/goalkeeper.py
hertz_packet/notice/log.py
hertz_packet/recall/__init__.py
hertz_packet/recall/mysql.py
hertz_packet-2.6.0.dist-info/LICENSE
hertz_packet-2.6.0.dist-info/METADATA
hertz_packet-2.6.0.dist-info/WHEEL
hertz_packet-2.6.0.dist-info/RECORD
