Metadata-Version: 2.1
Name: hertz_packet
Version: 2.6.0
Summary: release Hertz
License: MIT
Author: luke9012
Author-email: luke781520097@163.com
Requires-Python: >=3.6
Classifier: License :: OSI Approved :: MIT License
Classifier: Programming Language :: Python :: 3
Classifier: Programming Language :: Python :: 3.6
Classifier: Programming Language :: Python :: 3.7
Classifier: Programming Language :: Python :: 3.8
Classifier: Programming Language :: Python :: 3.9
Classifier: Programming Language :: Python :: 3.10
Classifier: Programming Language :: Python :: 3.11
Classifier: Programming Language :: Python :: 3.12
Requires-Dist: pymysql (>=1.0.3)
Requires-Dist: requests (>=2.27.1)
Requires-Dist: schedule (>=1.2.1)
